PyLinkbot3-3.0.0a2.dist-info/DESCRIPTION.rst
PyLinkbot3-3.0.0a2.dist-info/METADATA
PyLinkbot3-3.0.0a2.dist-info/RECORD
PyLinkbot3-3.0.0a2.dist-info/WHEEL
PyLinkbot3-3.0.0a2.dist-info/metadata.json
PyLinkbot3-3.0.0a2.dist-info/top_level.txt
linkbot3/__init__.py
linkbot3/_util.py
linkbot3/peripherals.py
linkbot3/async/__init__.py
linkbot3/async/commontypes_pb2.py
linkbot3/async/daemon_pb2.py
linkbot3/async/peripherals.py
linkbot3/async/robot_pb2.py
