Metadata-Version: 2.0
Name: PyLinkbot3
Version: 3.0.0a2
Summary: This is a pure Python implementation of PyLinkbot. See http://github.com/BaroboRobotics/PyLinkbot
Home-page: http://github.com/BaroboRobotics/PyLinkbot3
Author: David Ko
Author-email: david@barobo.com
License: UNKNOWN
Platform: UNKNOWN
Classifier: Development Status :: 3 - Alpha
Classifier: Intended Audience :: Education
Classifier: Operating System :: OS Independent
Classifier: Programming Language :: Python :: 3.5
Requires-Dist: PyRibbonBridge (>=0.0.6)
Requires-Dist: PySfp (>=0.1.1)
Requires-Dist: websockets (>=3.0)
